testsemrelease/__init__.py
testsemrdcline-0.8.7.dist-info/METADATA
testsemrdcline-0.8.7.dist-info/WHEEL
testsemrdcline-0.8.7.dist-info/RECORD
