Metadata-Version: 2.1
Name: testsemrdcline
Version: 0.8.7
Summary: Test package to release with the poetry-semantic-release action
Author: Danelle Cline
Author-email: dcline@mbari.org
Requires-Python: >=3.9,<3.12
Classifier: Programming Language :: Python :: 3
Classifier: Programming Language :: Python :: 3.9
Classifier: Programming Language :: Python :: 3.10
Classifier: Programming Language :: Python :: 3.11
